nangs/__init__.py
nangs/history.py
nangs/kk.py
nangs/pde.py
nangs/solver.py
nangs/utils.py
nangs/bocos/__init__.py
nangs/bocos/boco.py
nangs/bocos/dirichlet.py
nangs/bocos/neumann.py
nangs/bocos/periodic.py
nangs/data/__init__.py
nangs/data/mesh.py
nangs/nn/__init__.py
nangs/nn/mlp.py
nangs-0.1.2.dist-info/LICENSE
nangs-0.1.2.dist-info/METADATA
nangs-0.1.2.dist-info/WHEEL
nangs-0.1.2.dist-info/entry_points.txt
nangs-0.1.2.dist-info/top_level.txt
nangs-0.1.2.dist-info/RECORD
