Metadata-Version: 2.1
Name: nangs
Version: 0.1.2
Summary: Solving Partial Differential Equations with Neural Networks
Home-page: https://github.com/juansensio/nangs
Author: Juan B. Pedro
Author-email: sensioai@gmail.com
License: Apache Software License 2.0
Keywords: Partial Differential Equations Neural Networks
Platform: UNKNOWN
Classifier: Development Status :: 3 - Alpha
Classifier: Intended Audience :: Developers
Classifier: License :: OSI Approved :: Apache Software License
Classifier: Natural Language :: English
Classifier: Programming Language :: Python :: 3.6
Classifier: Programming Language :: Python :: 3.7
Classifier: Programming Language :: Python :: 3.8
Requires-Python: >=3.6
